jacaranda/__init__.py
jacaranda/pytorch.py
jacaranda/xgboost.py
jacaranda-0.0.1.dist-info/LICENSE.md
jacaranda-0.0.1.dist-info/METADATA
jacaranda-0.0.1.dist-info/WHEEL
jacaranda-0.0.1.dist-info/top_level.txt
jacaranda-0.0.1.dist-info/RECORD
