Metadata-Version: 2.1
Name: jacaranda
Version: 0.0.1
Summary: Jacaranda Python Library
Author-email: Harry Goodman <harryfgoodman@gmail.com>, Gabriel Dennis <gabrieldennis17@gmail.com>
License: MIT
Requires-Python: >=3.8.1
License-File: LICENSE.md
Requires-Dist: scipy (==1.7.0)
Requires-Dist: pandas
Requires-Dist: numpy
Requires-Dist: torch
Requires-Dist: optuna
Requires-Dist: scikit-learn
Requires-Dist: xgboost
